iloveflask/__init__.py
iloveflask/main.py
report/API.py
report/Attribut.py
report/Function.py
report/__init__.py
iloveflask-0.1.1.dist-info/LICENSE
iloveflask-0.1.1.dist-info/METADATA
iloveflask-0.1.1.dist-info/WHEEL
iloveflask-0.1.1.dist-info/top_level.txt
iloveflask-0.1.1.dist-info/RECORD
